Metadata-Version: 2.1
Name: cruel
Version: 0.0.12
Summary: Cruel - Scrape everything or anything from the web.
Home-page: https://github.com/Bishwas-py/cruel
Author: Bishwas Bhandari
Author-email: yo@bishwas.net
Classifier: Programming Language :: Python :: 3
Classifier: Programming Language :: Python :: 3.6
Classifier: Programming Language :: Python :: 3.7
Classifier: Programming Language :: Python :: 3.9
Classifier: License :: OSI Approved :: GNU General Public License v3 (GPLv3)
Classifier: Operating System :: OS Independent
License-File: LICENCE
Requires-Dist: beautifulsoup4~=4.12.2
Requires-Dist: certifi~=2023.7.22
Requires-Dist: charset-normalizer~=3.2.0
Requires-Dist: html5lib~=1.1
Requires-Dist: idna~=3.4
Requires-Dist: requests~=2.31.0
Requires-Dist: six~=1.16.0
Requires-Dist: soupsieve~=2.4.1
Requires-Dist: urllib3~=2.0.4
Requires-Dist: webencodings~=0.5.1
